MANIFEST.in
setup.cfg
setup.py
versioneer.py
toolbelt/__init__.py
toolbelt/_version.py
toolbelt.egg-info/PKG-INFO
toolbelt.egg-info/SOURCES.txt
toolbelt.egg-info/dependency_links.txt
toolbelt.egg-info/top_level.txt