Metadata-Version: 1.1
Name: toolbelt
Version: 0.1.0
Summary: A place to hold python tools.
Home-page: https://github.com/kadrlica/toolbelt
Author: Alex Drlica-Wagner
Author-email: kadrlica@fnal.gov
License: UNKNOWN
Keywords: python tools
Platform: any
Classifier: Programming Language :: Python
Classifier: Development Status :: 2 - Pre-Alpha
Classifier: Natural Language :: English
Classifier: Intended Audience :: Science/Research
